verily/__init__.py
verily/display.py
verily/io.py
verily/main.py
verily/models.py
verily/runner.py
verily/stats.py
verily/utils.py
verily-0.1.2.dist-info/METADATA
verily-0.1.2.dist-info/WHEEL
verily-0.1.2.dist-info/entry_points.txt
verily-0.1.2.dist-info/licenses/LICENSE
verily-0.1.2.dist-info/RECORD
